streaminghub_codec_avro/__init__.py
streaminghub_codec_avro/codec.py
streaminghub_codec_avro-0.0.1.dist-info/METADATA
streaminghub_codec_avro-0.0.1.dist-info/WHEEL
streaminghub_codec_avro-0.0.1.dist-info/entry_points.txt
streaminghub_codec_avro-0.0.1.dist-info/top_level.txt
streaminghub_codec_avro-0.0.1.dist-info/RECORD
